nisupply/__init__.py
nisupply/bids.py
nisupply/io.py
nisupply/utils.py
nisupply-2023.3.10.dist-info/LICENSE
nisupply-2023.3.10.dist-info/METADATA
nisupply-2023.3.10.dist-info/WHEEL
nisupply-2023.3.10.dist-info/top_level.txt
nisupply-2023.3.10.dist-info/RECORD
