Metadata-Version: 2.1
Name: nisupply
Version: 2023.3.10
Summary: A python module for dealing with unstructured or semi-structured neuroimaging datasets which do not conform to the BIDS data structure
Author-email: Johannes Wiesner <joh.wiesner@gmail.com>
License: MIT
Project-URL: Homepage, https://github.com/JohannesWiesner/nisupply
Keywords: files,utility,neuroscience,neuroimaging,file-management
Classifier: Programming Language :: Python :: 3
Classifier: License :: OSI Approved :: MIT License
Classifier: Operating System :: OS Independent
License-File: LICENSE
Requires-Dist: numpy
Requires-Dist: pandas
